gondola_cxx/__init__.py
gondola_cxx/gondola_cxx.cpython-313-x86_64-linux-gnu.so
gondola_cxx-0.11.0.dist-info/METADATA
gondola_cxx-0.11.0.dist-info/WHEEL
gondola_cxx-0.11.0.dist-info/RECORD
gondola_cxx-0.11.0.dist-info/licenses/LICENSE
