Metadata-Version: 2.2
Name: gondola_cxx
Version: 0.11.0
Summary: C++ compatibility layer for gondola
License: # GNU GENERAL PUBLIC LICENSE
Classifier: Programming Language :: Python :: 3
Classifier: Programming Language :: C++
Classifier: Operating System :: OS Independent
Requires-Python: >=3.8
